justanything/__init__.py
justanything-0.1.0.dist-info/licenses/LICENSE
justanything-0.1.0.dist-info/METADATA
justanything-0.1.0.dist-info/WHEEL
justanything-0.1.0.dist-info/top_level.txt
justanything-0.1.0.dist-info/RECORD
